tdh_twitch_utils-1.8.2.dist-info/licenses/LICENSE
twitch_utils/__init__.py
twitch_utils/__main__.py
twitch_utils/clip.py
twitch_utils/concat.py
twitch_utils/hls.py
twitch_utils/mute.py
twitch_utils/offset.py
twitch_utils/record.py
twitch_utils/twitch.py
twitch_utils/utils.py
twitch_utils/vod.py
tdh_twitch_utils-1.8.2.dist-info/METADATA
tdh_twitch_utils-1.8.2.dist-info/WHEEL
tdh_twitch_utils-1.8.2.dist-info/entry_points.txt
tdh_twitch_utils-1.8.2.dist-info/top_level.txt
tdh_twitch_utils-1.8.2.dist-info/RECORD
