Metadata-Version: 2.4
Name: tdh-twitch-utils
Version: 1.8.2
Summary: Record, concatenate and synchronize Twitch live streams
Home-page: https://github.com/TheDrHax/Twitch-Utils
Author: Dmitry Karikh
Author-email: the.dr.hax@gmail.com
Classifier: Environment :: Console
Classifier: Programming Language :: Python :: 3.6
Classifier: Intended Audience :: End Users/Desktop
Classifier: Intended Audience :: Developers
Classifier: License :: OSI Approved :: GNU General Public License v3 (GPLv3)
Classifier: Topic :: Multimedia :: Sound/Audio :: Analysis
Classifier: Topic :: Multimedia :: Video :: Conversion
Classifier: Topic :: Utilities
License-File: LICENSE
Requires-Dist: requests
Requires-Dist: retry-requests
Requires-Dist: python-dateutil
Requires-Dist: docopt>=0.6.2
Provides-Extra: record
Requires-Dist: streamlink>=7.4.0; extra == "record"
Requires-Dist: parse>=1.19.0; extra == "record"
Provides-Extra: offset
Requires-Dist: praat-parselmouth>=0.4; extra == "offset"
Provides-Extra: mute
Requires-Dist: spleeter>=2.3.0; extra == "mute"
Provides-Extra: all
Requires-Dist: streamlink>=7.4.0; extra == "all"
Requires-Dist: parse>=1.19.0; extra == "all"
Requires-Dist: praat-parselmouth>=0.4; extra == "all"
Requires-Dist: spleeter>=2.3.0; extra == "all"
Dynamic: author
Dynamic: author-email
Dynamic: classifier
Dynamic: description
Dynamic: description-content-type
Dynamic: home-page
Dynamic: license-file
Dynamic: provides-extra
Dynamic: requires-dist
Dynamic: summary
